process_tracker/__init__.py
process_tracker/_internal/libpreload.so
process_tracker/_internal/__init__.py
process_tracker/_internal/_process_tracker.cpython-37m-x86_64-linux-gnu.so
process_tracker/_internal/includes/__init__.py
process_tracker-0.1.2.dist-info/RECORD
process_tracker-0.1.2.dist-info/LICENSE
process_tracker-0.1.2.dist-info/top_level.txt
process_tracker-0.1.2.dist-info/METADATA
process_tracker-0.1.2.dist-info/WHEEL
