Metadata-Version: 2.1
Name: process-tracker
Version: 0.1.2
Summary: Track child processes.
Home-page: https://github.com/chrahunt/process-tracker
Author: Chris Hunt
Author-email: chrahunt@gmail.com
License: UNKNOWN
Platform: UNKNOWN
Classifier: Development Status :: 3 - Alpha
Classifier: Intended Audience :: Developers
Classifier: License :: OSI Approved :: MIT License
Classifier: Operating System :: POSIX :: Linux
Classifier: Programming Language :: C
Provides-Extra: dev
Requires-Dist: cmake ; extra == 'dev'
Requires-Dist: Cython ; extra == 'dev'
Requires-Dist: ninja ; extra == 'dev'
Requires-Dist: pytest ; extra == 'dev'
Requires-Dist: pytest-forked ; extra == 'dev'
Requires-Dist: scikit-build ; extra == 'dev'
Requires-Dist: setuptools ; extra == 'dev'
Requires-Dist: tox ; extra == 'dev'
